ad9958_vars.vh
`ifndef _AD9958_VARS_VH_

`define _AD9958_VARS_VH_

`define IOMODE_2_WIRE 2'b00
`define IOMODE_3_WIRE 2'b01
`define IOMODE_2_BIT 2'b10
`define IOMODE_4_BIT 2'b11

`define DAC_FSCALE_FULL 2'b11
`define DAC_FSCALE_HALF 2'b01
`define DAC_FSCALE_QUARTER 2'b10
`define DAC_FSCALE_EIGHTH 2'b00

`endif

ad9958_config_register.v
`timescale 1ns / 1ps
/*
 * ad9958_config_register.v
 * 
 * temporaly, this module just returns default values.
 * ref_clk = 30 MHz, clock_multiplier = 10
 * sys_clk = 30 * 10 MHz -> vco gain = enabled
 */
`include "ad9958_vars.vh"

module ad9958_config_register(
							  output reg 	   vco_gain,
							  output reg [4:0] clock_multiplier,
							  output reg [1:0] dac_fscale_ch0,
							  output reg [1:0] dac_fscale_ch1
);
   initial begin
	  vco_gain = 1'b1;
	  clock_multiplier = 5'd10;
	  dac_fscale_ch0 = `DAC_FSCALE_HALF;
	  dac_fscale_ch1 = `DAC_FSCALE_HALF;
   end
   
endmodule

spi_send_only.v
`timescale 1ns / 1ps
/* PASSED TEST */

/*
 * Send-only-spi module
 * 1 pack (= 4 bit) of data are read every posedge of sclk.
 * Send only, Clock stall high, update sdio on negedge of sclk.
 * Data is sent in LSB first
 * packs[0] -> sdio[0]
 * packs[1] -> sdio[1]
 * ..
 * 
 * Usage of this module
 * 1. Set data to send on data_input and packs_to_send. see manual for AD9958.
 * 2. set trigger high when busy is low.
 * 3. wait for busy turn to low before sending next data.
 */
module spi_send_only(
					 input 			  clock,
					 input 			  reset_n,
					 input 			  trigger,
					 output reg 	  busy,
					 input [4:0] 	  packs_to_send,
					 // 
					 input [63:0] 	  data_input,
					 // SPI interface
					 output reg 	  cs,
					 output reg 	  sclk,
					 output reg [3:0] sdio
);
   /* STATEMACHINE DEFINITION */
   parameter
	 STATE_IDLE = 0,
	 STATE_SEND = 1;

   reg 								  state;
   reg [4:0] 						  packs_cntr;

   // Send buffer
   reg [63:0] 						  data_send;
   
   
   // set to low by default
   //assign sdio = 4'b0;
   // clock stall high
   //assign sclk = 1'b1;
   
   always @(posedge clock) begin
	  if(~reset_n) begin
		 cs <= 0; // assuming single device is connected.		 
		 state <= STATE_IDLE;
		 busy <= 1;
		 sclk <= 1'b1;
		 sdio <= 4'b0;
		 packs_cntr <= 5'b0;
	  end else begin
		 case(state)
		   STATE_IDLE : begin
			  if(trigger & ~busy) begin
				 state <= STATE_SEND;
				 busy <= 1;
				 packs_cntr <= packs_to_send;
				 data_send <= data_input;				 
			  end else begin
				 busy <= 0;
				 sclk <= 1'b1;
				 sdio <= 4'b0;
				 packs_cntr <= 5'b0;
			  end // else: !if(trigger & ~busy)
		   end // case: STATE_IDLE
		   
		   STATE_SEND : begin
			  sclk <= 1'b0;
		   end
		   
		   default : begin
		   end
		 endcase // case (state)
	  end // else: !if(~reset_n)
   end // always @ (posedge clock)

   always @(negedge clock)begin
	  if(~reset_n) begin
	  end else begin
		 case(state)
		   STATE_IDLE : begin
		   end

		   STATE_SEND : begin
			  sclk <= 1'b1;
		   end

		   default :begin
		   end

		 endcase // case (state)
	  end // else: !if(~reset_n)
   end // always @ (negedge clock)

   /*
	* Update sdio registers.
	*/
   always @(negedge sclk) begin
	  if(~reset_n) begin
		 sdio <= 4'b0;
	  end else begin
		 case (state)
		   STATE_IDLE : begin
		   end

		   STATE_SEND : begin
			  // once sdio is updated, shift data_send @ posedge of sclk
			  sdio[0] <= data_send[0];
			  sdio[1] <= data_send[1];
			  sdio[2] <= data_send[2];
			  sdio[3] <= data_send[3];

			  packs_cntr <= packs_cntr - 1;
		   end

		   default : begin
		   end
		 endcase // case (state)
	  end // else: !if(~reset_n)
   end // always @ (negedge sclk)

   always @(posedge sclk) begin
	  case (state)
		STATE_IDLE :begin
		end

		STATE_SEND : begin
		   if(packs_cntr == 0) begin
			  data_send <= 64'h0;
			  state <= STATE_IDLE;
		   end else begin
			  // shift data for next pack
			  //data_send <= {4'b0, data_send[32:4]};
			  data_send <= (data_send >> 4);
		   end
		end
	  endcase // case (state)
   end // always @ (posedge sclk)
endmodule // spi_send_only

ad9958_registers.vh
/*
 * Registers accessed in this project is listed here.
 */

`ifndef _AD9958_ADDRESS_VH_

`define _AD9958_ADDRESS_VH_

`define ADDR_CSR 8'h00
`define ADDR_FR1 8'h01
`define ADDR_FR2 8'h02
`define ADDR_CFR 8'h03
`define ADDR_CFTW0 8'h04
`define ADDR_ACR 8'h06

`define SIZE_INST 2
`define SIZE_CSR 2
`define SIZE_FR1 6
`define SIZE_FR2 4
`define SIZE_CFR 6
`define SIZE_CFTW0 8
`define SIZE_ACR 4
`endif

ad9958_core.v
`timescale 1ns / 1ps
/*
 * ad9958_core.v
 * 
 */
`include "ad9958_registers.vh"
`include "ad9958_vars.vh"

module ad9958_core(
				   input 			 clock,
				   input 			 reset_n,
				   // input from ftw, asf buffer registers.
				   input [32-1:0] 	 ftw_ch0,
				   input [32-1:0] 	 ftw_ch1,
				   input [32-1:0] 	 asf_ch0,
				   input [32-1:0] 	 asf_ch1,

				   // input from initizalization configuration registers.
				   input 			 vco_gain,
				   input [4:0] 		 clock_multiplier,
				   // dac_fscale_ch1 is ignored
				   input [1:0] 		 dac_fscale_ch0,
				   input [1:0] 		 dac_fscale_ch1,

				   input 			 busy,

				   output reg 		 trigger,
				   output reg [4:0]  packs_to_send,
				   output reg [63:0] data_input,

				   output reg 		 master_reset,
				   output reg 		 io_update
				   );

   // Configuration bits.
   parameter
	 MSB_FIRST = 0,
	 LSB_FIRST = 1;

   parameter
	 CH0_ENABLE = 8'b01000000,
	 CH1_ENABLE = 8'b10000000;

   parameter
	 IO_MODE = `IOMODE_4_BIT;

   
   /* STATEMACHINE DEFINITION */
   /*
	* soon after initialization is completed, this module moves to main loop of just setting asf and ftw.
	*/
   parameter
	 STATE_MASTER_RESET = 0,
	 STATE_IO_UPDATE = 1,
	 STATE_INSTRUCTION_WRITE = 2,
	 STATE_CSR_CONFIG = 3,
	 STATE_FR1_CONFIG = 4,
	 STATE_FR2_CONFIG = 5,
	 STATE_CFR_CONFIG = 6,
	 STATE_FTW_CONFIG = 7,
	 STATE_ASF_CONFIG = 8,
	 STATE_WAIT = 9;
   
   parameter
	 NONE_SELECTED = 0,
	 CH0_SELECTED = 1,
	 CH1_SELECTED = 2,
	 BOTH_SELECTED = 3;

   parameter
	 TUNE_FREQ = 0,
	 TUNE_AMPL = 1;
   
   reg 								 init_done;
   reg [1:0] 						 channel_select;   

   reg [3:0] 						 state;
   reg [3:0] 						 next_state;
   
   reg [7:0] 						 reg_address;

   reg [1:0] 						 tune_target;
   
   reg [32-1:0] 					 ftw_ch0_buf;
   reg [32-1:0] 					 ftw_ch1_buf;
   reg [32-1:0] 					 asf_ch0_buf;
   reg [32-1:0] 					 asf_ch1_buf;

   // Update internal buffer on io update, because next dds update sequence begins soon after io update.
   always @(posedge io_update) begin
	  ftw_ch0_buf <= ftw_ch0;
	  ftw_ch1_buf <= ftw_ch1;

	  asf_ch0_buf <= asf_ch0;
	  asf_ch1_buf <= asf_ch1;
   end

   always @(posedge clock) begin
	  if(~reset_n) begin
		 init_done <= 0;
		 master_reset <= 1;
		 state <= STATE_MASTER_RESET;
		 
	  end else begin
		 case(state)
		   STATE_MASTER_RESET : begin
			  master_reset <= 1;
			  state <= STATE_INSTRUCTION_WRITE;
			  next_state <= STATE_CSR_CONFIG;
			  channel_select <= NONE_SELECTED;
			  reg_address <= `ADDR_CSR;
			  tune_target <= TUNE_FREQ;

		   end

		   STATE_IO_UPDATE : begin
			  io_update <= 1;
			  state <= STATE_WAIT;
			  next_state <= STATE_INSTRUCTION_WRITE;
			  
			  if(init_done) begin
				 reg_address <= `ADDR_CSR;
				 channel_select <= CH0_SELECTED;
			  end else begin
				 reg_address <= `ADDR_CFR;
			  end
		   end // case: STATE_IO_UPDATE

		   STATE_INSTRUCTION_WRITE : begin
			  state <= STATE_WAIT;
			  master_reset <= 0;

			  trigger <= 1;
			  data_input <= reg_address | `INSTRUCTION_WRITE;
			  packs_to_send <= `SIZE_INST;
			  
			  case(reg_address)
				`ADDR_CSR : begin
				   next_state <= STATE_CSR_CONFIG;
				end
				`ADDR_FR1 : begin
				   next_state <= STATE_FR1_CONFIG;
				end
				`ADDR_FR2 : begin
				   next_state <= STATE_FR2_CONFIG;
				end
				`ADDR_CFR : begin
				   next_state <= STATE_CFR_CONFIG;
				end
				`ADDR_CFTW0 : begin
				   next_state <= STATE_FTW_CONFIG;
				end
				`ADDR_ACR : begin
				   next_state <= STATE_ASF_CONFIG;
				end
				default : begin
				   next_state <= STATE_INSTRUCTION_WRITE;
				end
			  endcase // case (reg_address)
			  
		   end // case: STATE_INSTRUCTION_WRITE

		   STATE_CSR_CONFIG : begin
			  state <= STATE_WAIT;
			  next_state <= STATE_INSTRUCTION_WRITE;

			  trigger <= 1;

			  packs_to_send <= `SIZE_CSR;
			  
			  case (channel_select)
				CH0_SELECTED : begin
				   // LSB first.
				   data_input <= CH0_ENABLE | LSB_FIRST | IO_MODE;
				   case(tune_target)
					 TUNE_FREQ : begin
						reg_address <= `ADDR_CFTW0;
					 end
					 TUNE_AMPL :begin
						reg_address <= `ADDR_ACR;
					 end
				   endcase
				end

				CH1_SELECTED : begin
				   data_input <= CH1_ENABLE | MSB_FIRST | IO_MODE;
				   case(tune_target)
					 TUNE_FREQ : begin
						reg_address <= `ADDR_CFTW0;
					 end
					 TUNE_AMPL :begin
						reg_address <= `ADDR_ACR;
					 end
				   endcase
				end
				
				default : begin /*NONE_SELECTED*/
				   data_input <= MSB_FIRST | IO_MODE;
				   reg_address <= `ADDR_FR1;
				end
			  endcase // case (channel_select)
		   end // case: STATE_CSR_CONFIG

		   STATE_FR1_CONFIG : begin
			  state <= STATE_WAIT;
			  next_state <= STATE_IO_UPDATE;
			  reg_address <= `ADDR_CSR;

			  trigger <= 1;
			  packs_to_send <= `SIZE_FR1;
			  data_input <= (vco_gain << 23) | (clock_multiplier << 18);
			  
		   end

		   // this state will be ignored, if needed, change reg_address assignments in STATE_FR1_CONFIG from ADDR_CSR to ADDR_FR2 and next_state from STATE_IO_UPDATE to STATE_INSTRUCTION_WRITE
		   STATE_FR2_CONFIG : begin
			  state <= STATE_WAIT;
			  next_state <= STATE_IO_UPDATE;
			  reg_address <= `ADDR_CSR;
		   end

		   STATE_CFR_CONFIG : begin
			  state <= STATE_WAIT;
			  next_state <= STATE_IO_UPDATE;
			  init_done <= 1;

			  trigger <= 1;

			  packs_to_send <= `SIZE_CFR;
			  data_input <= (dac_fscale_ch0 << 8);
			  
			  reg_address <= `ADDR_CSR;
		   end // case: STATE_CFR_CONFIG

		   STATE_FTW_CONFIG : begin
			  state <= STATE_WAIT;
			  next_state <= STATE_INSTRUCTION_WRITE;

			  trigger <= 1;
			  packs_to_send <= `SIZE_CFTW0;
			  
			  case(channel_select)
				CH0_SELECTED : begin
				   channel_select <= CH1_SELECTED;
				   data_input <= ftw_ch0_buf;
				   next_state <= STATE_INSTRUCTION_WRITE;
				   tune_target <= TUNE_FREQ;

				end
				CH1_SELECTED : begin
				   channel_select <= CH0_SELECTED;
				   data_input <= ftw_ch1_buf;
				   next_state <= STATE_IO_UPDATE;
				   tune_target <= TUNE_AMPL;

				end
				default : begin
				   // THIS IS EXCEPTION, DO NOTHING
				end
			  endcase // case (channel_select)
//			  reg_address <= `ADDR_ACR;
			  reg_address <= `ADDR_CSR;
			  // case (channel_select)
		   end // case: STATE_FTW_CONFIG

		   STATE_ASF_CONFIG : begin
			  state <= STATE_WAIT;

			  trigger <= 1;
			  packs_to_send <= `SIZE_ACR;
			  
			  case (channel_select)
				CH0_SELECTED : begin
				   channel_select <= CH1_SELECTED;
				   // only channel0 is configured, configure channel1 without issuing io_update.
				   next_state <= STATE_INSTRUCTION_WRITE;
				   data_input <= asf_ch0_buf;
				   tune_target <= TUNE_AMPL;

				end

				CH1_SELECTED : begin
				   channel_select <= CH0_SELECTED;
				   // both channels are configured, issue io_update to reflect changes.
				   next_state <= STATE_IO_UPDATE;
				   data_input <= asf_ch1_buf;
				   tune_target <= TUNE_FREQ;
				end
				default : begin
				   channel_select <= CH0_SELECTED;
				end
			  endcase // case (channel_select)
			  
			  reg_address <= `ADDR_CSR;
		   end // case: STATE_ASF_CONFIG

		   STATE_WAIT : begin
			  master_reset <= 0;
			  io_update <= 0;
			  trigger <= 0;
			  // wait for spi data transfer to complete
			  if(~ (busy | trigger)) begin
				 state <= next_state;
			  end
		   end
		   default : begin
		   end
		 endcase // case (state)
	  end // else: !if(~reset_n)
   end // always @ (posedge clock)
endmodule // ad9958_core

ad9958_master.v
`timescale 1ns / 1ps

module ad9958_master(
					 input 			  clock,
					 input 			  reset_n,

					 output 		  cs,
					 output 		  sclk,
					 output [3:0] 	  sdio,

					 output 		  master_reset,
					 output 		  io_update,


					 input [32-1:0] ftw_ch0,
					 input [32-1:0] ftw_ch1,
					 input [10-1:0] asf_ch0,
					 input [10-1:0] asf_ch1
);
   /*AUTOWIRE*/
   // Beginning of automatic wires (for undeclared instantiated-module outputs)
   wire					busy;					// From spi_master of spi_send_only.v
   wire [4:0]			clock_multiplier;		// From config_register of ad9958_config_register.v
   wire [1:0]			dac_fscale_ch0;			// From config_register of ad9958_config_register.v
   wire [1:0]			dac_fscale_ch1;			// From config_register of ad9958_config_register.v
   wire [63:0]			data_input;				// From ad9958_core_inst of ad9958_core.v
   wire [4:0]			packs_to_send;			// From ad9958_core_inst of ad9958_core.v
   wire					trigger;				// From ad9958_core_inst of ad9958_core.v
   wire					vco_gain;				// From config_register of ad9958_config_register.v
   // End of automatics
   
   ad9958_core ad9958_core_inst(/*AUTOINST*/
								// Outputs
								.trigger		(trigger),
								.packs_to_send	(packs_to_send[4:0]),
								.data_input		(data_input[63:0]),
								.master_reset	(master_reset),
								.io_update		(io_update),
								// Inputs
								.clock			(clock),
								.reset_n		(reset_n),
								.ftw_ch0		(ftw_ch0[32-1:0]),
								.ftw_ch1		(ftw_ch1[32-1:0]),
								.asf_ch0		(asf_ch0[10-1:0]),
								.asf_ch1		(asf_ch1[10-1:0]),
								.vco_gain		(vco_gain),
								.clock_multiplier(clock_multiplier[4:0]),
								.dac_fscale_ch0	(dac_fscale_ch0[1:0]),
								.dac_fscale_ch1	(dac_fscale_ch1[1:0]),
								.busy			(busy));
   

   spi_send_only spi_master(/*AUTOINST*/
							// Outputs
							.busy				(busy),
							.cs					(cs),
							.sclk				(sclk),
							.sdio				(sdio[3:0]),
							// Inputs
							.clock				(clock),
							.reset_n			(reset_n),
							.trigger			(trigger),
							.packs_to_send		(packs_to_send[4:0]),
							.data_input			(data_input[63:0]));

   ad9958_config_register config_register(/*AUTOINST*/
										  // Outputs
										  .vco_gain				(vco_gain),
										  .clock_multiplier		(clock_multiplier[4:0]),
										  .dac_fscale_ch0		(dac_fscale_ch0[1:0]),
										  .dac_fscale_ch1		(dac_fscale_ch1[1:0]));

endmodule

ad9958_master_tb.v
`timescale 1ns / 1ps

module ad9958_master_tb;

   wire cs;
   wire sclk;
   wire [3:0] sdio;
   wire 	  master_reset;
   wire 	  io_update;

   reg 		  clock;
   reg 		  reset_n;

   reg [32-1:0] ftw_ch0;
   reg [32-1:0] ftw_ch1;
   reg [32-1:0] asf_ch0;
   reg [32-1:0] asf_ch1;

   ad9958_master ad9958_master_inst(/*AUTOINST*/
									// Outputs
									.cs					(cs),
									.sclk				(sclk),
									.sdio				(sdio[3:0]),
									.master_reset		(master_reset),
									.io_update			(io_update),
									// Inputs
									.clock				(clock),
									.reset_n			(reset_n),
									.ftw_ch0			(ftw_ch0[32-1:0]),
									.ftw_ch1			(ftw_ch1[32-1:0]),
									.asf_ch0			(asf_ch0[32-1:0]),
									.asf_ch1			(asf_ch1[32-1:0]));

   always begin
	  #10 	 clock = ~clock;
   end

   always @(posedge clock) begin
	  ftw_ch0 <= ftw_ch0 + 10;
	  ftw_ch1 <= ftw_ch1 + 10;
	  asf_ch0 <= asf_ch0 + 20;
	  asf_ch1 <= asf_ch1 + 20;
   end

   initial begin
	  $dumpfile("ad9958_master.vcd");
	  $dumpvars(0, ad9958_master_tb);

	  $display("START");
	  clock <= 0;
	  reset_n <= 0;

	  ftw_ch0 <= 0;
	  ftw_ch1 <= 0;
	  asf_ch0 <= 0;
	  asf_ch1 <= 0;
	  
	  #100 reset_n <= 1;


	  #100000
		$display("END");
	  $finish;	  
	  
   end // initial begin

endmodule

ad9958_master.vcd
$date
	Thu Jan 24 15:18:10 2019
$end
$version
	Icarus Verilog
$end
$timescale
	1ps
$end
$scope module ad9958_master_tb $end
$var wire 4 ! sdio [3:0] $end
$var wire 1 " sclk $end
$var wire 1 # master_reset $end
$var wire 1 $ io_update $end
$var wire 1 % cs $end
$var reg 32 & asf_ch0 [31:0] $end
$var reg 32 ' asf_ch1 [31:0] $end
$var reg 1 ( clock $end
$var reg 32 ) ftw_ch0 [31:0] $end
$var reg 32 * ftw_ch1 [31:0] $end
$var reg 1 + reset_n $end
$scope module ad9958_master_inst $end
$var wire 32 , asf_ch0 [31:0] $end
$var wire 32 - asf_ch1 [31:0] $end
$var wire 1 ( clock $end
$var wire 32 . ftw_ch0 [31:0] $end
$var wire 32 / ftw_ch1 [31:0] $end
$var wire 1 + reset_n $end
$var wire 1 0 vco_gain $end
$var wire 1 1 trigger $end
$var wire 4 2 sdio [3:0] $end
$var wire 1 " sclk $end
$var wire 5 3 packs_to_send [4:0] $end
$var wire 1 # master_reset $end
$var wire 1 $ io_update $end
$var wire 64 4 data_input [63:0] $end
$var wire 2 5 dac_fscale_ch1 [1:0] $end
$var wire 2 6 dac_fscale_ch0 [1:0] $end
$var wire 1 % cs $end
$var wire 5 7 clock_multiplier [4:0] $end
$var wire 1 8 busy $end
$scope module ad9958_core_inst $end
$var wire 32 9 asf_ch0 [31:0] $end
$var wire 32 : asf_ch1 [31:0] $end
$var wire 1 ( clock $end
$var wire 32 ; ftw_ch0 [31:0] $end
$var wire 32 < ftw_ch1 [31:0] $end
$var wire 1 + reset_n $end
$var wire 1 0 vco_gain $end
$var wire 2 = dac_fscale_ch1 [1:0] $end
$var wire 2 > dac_fscale_ch0 [1:0] $end
$var wire 5 ? clock_multiplier [4:0] $end
$var wire 1 8 busy $end
$var reg 32 @ asf_ch0_buf [31:0] $end
$var reg 32 A asf_ch1_buf [31:0] $end
$var reg 2 B channel_select [1:0] $end
$var reg 64 C data_input [63:0] $end
$var reg 32 D ftw_ch0_buf [31:0] $end
$var reg 32 E ftw_ch1_buf [31:0] $end
$var reg 1 F init_done $end
$var reg 1 $ io_update $end
$var reg 1 # master_reset $end
$var reg 4 G next_state [3:0] $end
$var reg 5 H packs_to_send [4:0] $end
$var reg 8 I reg_address [7:0] $end
$var reg 4 J state [3:0] $end
$var reg 1 1 trigger $end
$var reg 2 K tune_target [1:0] $end
$upscope $end
$scope module config_register $end
$var reg 5 L clock_multiplier [4:0] $end
$var reg 2 M dac_fscale_ch0 [1:0] $end
$var reg 2 N dac_fscale_ch1 [1:0] $end
$var reg 1 0 vco_gain $end
$upscope $end
$scope module spi_master $end
$var wire 1 ( clock $end
$var wire 64 O data_input [63:0] $end
$var wire 5 P packs_to_send [4:0] $end
$var wire 1 + reset_n $end
$var wire 1 1 trigger $end
$var reg 1 8 busy $end
$var reg 1 % cs $end
$var reg 64 Q data_send [63:0] $end
$var reg 5 R packs_cntr [4:0] $end
$var reg 1 " sclk $end
$var reg 4 S sdio [3:0] $end
$var reg 1 T state $end
$upscope $end
$upscope $end
$upscope $end
$enddefinitions $end
#0
$dumpvars
xT
bx S
bx R
bx Q
bx P
bx O
b1 N
b1 M
b1010 L
bx K
bx J
bx I
bx H
bx G
xF
bx E
bx D
bx C
bx B
bx A
bx @
b1010 ?
b1 >
b1 =
b0 <
b0 ;
b0 :
b0 9
x8
b1010 7
b1 6
b1 5
bx 4
bx 3
bx 2
x1
10
b0 /
b0 .
b0 -
b0 ,
0+
b0 *
b0 )
0(
b0 '
b0 &
x%
x$
x#
x"
bx !
$end
#10000
b0 J
1#
0F
b0 R
b0 !
b0 2
b0 S
1"
18
0T
0%
b10 '
b10 -
b10 :
b10 &
b10 ,
b10 9
b1 *
b1 /
b1 <
b1 )
b1 .
b1 ;
1(
#20000
0(
#30000
b100 '
b100 -
b100 :
b100 &
b100 ,
b100 9
b10 *
b10 /
b10 <
b10 )
b10 .
b10 ;
1(
#40000
0(
#50000
b110 '
b110 -
b110 :
b110 &
b110 ,
b110 9
b11 *
b11 /
b11 <
b11 )
b11 .
b11 ;
1(
#60000
0(
#70000
b1000 '
b1000 -
b1000 :
b1000 &
b1000 ,
b1000 9
b100 *
b100 /
b100 <
b100 )
b100 .
b100 ;
1(
#80000
0(
#90000
b1010 '
b1010 -
b1010 :
b1010 &
b1010 ,
b1010 9
b101 *
b101 /
b101 <
b101 )
b101 .
b101 ;
1(
#100000
1+
0(
#110000
b1100 '
b1100 -
b1100 :
b1100 &
b1100 ,
b1100 9
b110 *
b110 /
b110 <
b110 )
b110 .
b110 ;
08
b0 K
b0 I
b0 B
b11 G
b10 J
1(
#120000
0(
#130000
b10 3
b10 H
b10 P
b0 4
b0 C
b0 O
11
0#
b1001 J
b1110 '
b1110 -
b1110 :
b1110 &
b1110 ,
b1110 9
b111 *
b111 /
b111 <
b111 )
b111 .
b111 ;
1(
#140000
0(
#150000
b10000 '
b10000 -
b10000 :
b10000 &
b10000 ,
b10000 9
b1000 *
b1000 /
b1000 <
b1000 )
b1000 .
b1000 ;
b0 Q
b10 R
18
1T
01
0$
1(
#160000
0(
#170000
b1 R
0"
b10010 '
b10010 -
b10010 :
b10010 &
b10010 ,
b10010 9
b1001 *
b1001 /
b1001 <
b1001 )
b1001 .
b1001 ;
1(
#180000
1"
0(
#190000
b0 R
b10100 '
b10100 -
b10100 :
b10100 &
b10100 ,
b10100 9
b1010 *
b1010 /
b1010 <
b1010 )
b1010 .
b1010 ;
0"
1(
#200000
0T
1"
0(
#210000
08
b10110 '
b10110 -
b10110 :
b10110 &
b10110 ,
b10110 9
b1011 *
b1011 /
b1011 <
b1011 )
b1011 .
b1011 ;
1(
#220000
0(
#230000
b11000 '
b11000 -
b11000 :
b11000 &
b11000 ,
b11000 9
b1100 *
b1100 /
b1100 <
b1100 )
b1100 .
b1100 ;
b11 J
1(
#240000
0(
#250000
b1 I
b110 4
b110 C
b110 O
11
b10 G
b1001 J
b11010 '
b11010 -
b11010 :
b11010 &
b11010 ,
b11010 9
b1101 *
b1101 /
b1101 <
b1101 )
b1101 .
b1101 ;
1(
#260000
0(
#270000
b11100 '
b11100 -
b11100 :
b11100 &
b11100 ,
b11100 9
b1110 *
b1110 /
b1110 <
b1110 )
b1110 .
b1110 ;
b110 Q
b10 R
18
1T
01
1(
#280000
0(
#290000
b1 R
b110 !
b110 2
b110 S
0"
b11110 '
b11110 -
b11110 :
b11110 &
b11110 ,
b11110 9
b1111 *
b1111 /
b1111 <
b1111 )
b1111 .
b1111 ;
1(
#300000
b0 Q
1"
0(
#310000
b0 R
b0 !
b0 2
b0 S
b100000 '
b100000 -
b100000 :
b100000 &
b100000 ,
b100000 9
b10000 *
b10000 /
b10000 <
b10000 )
b10000 .
b10000 ;
0"
1(
#320000
0T
1"
0(
#330000
08
b100010 '
b100010 -
b100010 :
b100010 &
b100010 ,
b100010 9
b10001 *
b10001 /
b10001 <
b10001 )
b10001 .
b10001 ;
1(
#340000
0(
#350000
b100100 '
b100100 -
b100100 :
b100100 &
b100100 ,
b100100 9
b10010 *
b10010 /
b10010 <
b10010 )
b10010 .
b10010 ;
b10 J
1(
#360000
0(
#370000
b100 G
b1 4
b1 C
b1 O
11
b1001 J
b100110 '
b100110 -
b100110 :
b100110 &
b100110 ,
b100110 9
b10011 *
b10011 /
b10011 <
b10011 )
b10011 .
b10011 ;
1(
#380000
0(
#390000
b101000 '
b101000 -
b101000 :
b101000 &
b101000 ,
b101000 9
b10100 *
b10100 /
b10100 <
b10100 )
b10100 .
b10100 ;
b1 Q
b10 R
18
1T
01
1(
#400000
0(
#410000
b1 R
b1 !
b1 2
b1 S
0"
b101010 '
b101010 -
b101010 :
b101010 &
b101010 ,
b101010 9
b10101 *
b10101 /
b10101 <
b10101 )
b10101 .
b10101 ;
1(
#420000
b0 Q
1"
0(
#430000
b0 R
b0 !
b0 2
b0 S
b101100 '
b101100 -
b101100 :
b101100 &
b101100 ,
b101100 9
b10110 *
b10110 /
b10110 <
b10110 )
b10110 .
b10110 ;
0"
1(
#440000
0T
1"
0(
#450000
08
b101110 '
b101110 -
b101110 :
b101110 &
b101110 ,
b101110 9
b10111 *
b10111 /
b10111 <
b10111 )
b10111 .
b10111 ;
1(
#460000
0(
#470000
b110000 '
b110000 -
b110000 :
b110000 &
b110000 ,
b110000 9
b11000 *
b11000 /
b11000 <
b11000 )
b11000 .
b11000 ;
b100 J
1(
#480000
0(
#490000
b101010000000000000000000 4
b101010000000000000000000 C
b101010000000000000000000 O
b110 3
b110 H
b110 P
11
b0 I
b1 G
b1001 J
b110010 '
b110010 -
b110010 :
b110010 &
b110010 ,
b110010 9
b11001 *
b11001 /
b11001 <
b11001 )
b11001 .
b11001 ;
1(
#500000
0(
#510000
b110100 '
b110100 -
b110100 :
b110100 &
b110100 ,
b110100 9
b11010 *
b11010 /
b11010 <
b11010 )
b11010 .
b11010 ;
b101010000000000000000000 Q
b110 R
18
1T
01
1(
#520000
0(
#530000
b101 R
0"
b110110 '
b110110 -
b110110 :
b110110 &
b110110 ,
b110110 9
b11011 *
b11011 /
b11011 <
b11011 )
b11011 .
b11011 ;
1(
#540000
b10101000000000000000 Q
1"
0(
#550000
b100 R
b111000 '
b111000 -
b111000 :
b111000 &
b111000 ,
b111000 9
b11100 *
b11100 /
b11100 <
b11100 )
b11100 .
b11100 ;
0"
1(
#560000
b1010100000000000 Q
1"
0(
#570000
b11 R
0"
b111010 '
b111010 -
b111010 :
b111010 &
b111010 ,
b111010 9
b11101 *
b11101 /
b11101 <
b11101 )
b11101 .
b11101 ;
1(
#580000
b101010000000 Q
1"
0(
#590000
b10 R
b111100 '
b111100 -
b111100 :
b111100 &
b111100 ,
b111100 9
b11110 *
b11110 /
b11110 <
b11110 )
b11110 .
b11110 ;
0"
1(
#600000
b10101000 Q
1"
0(
#610000
b1 R
b1000 !
b1000 2
b1000 S
0"
b111110 '
b111110 -
b111110 :
b111110 &
b111110 ,
b111110 9
b11111 *
b11111 /
b11111 <
b11111 )
b11111 .
b11111 ;
1(
#620000
b1010 Q
1"
0(
#630000
b0 R
b1010 !
b1010 2
b1010 S
b1000000 '
b1000000 -
b1000000 :
b1000000 &
b1000000 ,
b1000000 9
b100000 *
b100000 /
b100000 <
b100000 )
b100000 .
b100000 ;
0"
1(
#640000
0T
b0 Q
1"
0(
#650000
b0 !
b0 2
b0 S
08
b1000010 '
b1000010 -
b1000010 :
b1000010 &
b1000010 ,
b1000010 9
b100001 *
b100001 /
b100001 <
b100001 )
b100001 .
b100001 ;
1(
#660000
0(
#670000
b1000100 '
b1000100 -
b1000100 :
b1000100 &
b1000100 ,
b1000100 9
b100010 *
b100010 /
b100010 <
b100010 )
b100010 .
b100010 ;
b1 J
1(
#680000
0(
#690000
b1000110 A
b1000110 @
b100011 E
b100011 D
b11 I
b10 G
b1001 J
1$
b1000110 '
b1000110 -
b1000110 :
b1000110 &
b1000110 ,
b1000110 9
b100011 *
b100011 /
b100011 <
b100011 )
b100011 .
b100011 ;
1(
#700000
0(
#710000
b1001000 '
b1001000 -
b1001000 :
b1001000 &
b1001000 ,
b1001000 9
b100100 *
b100100 /
b100100 <
b100100 )
b100100 .
b100100 ;
b10 J
0$
1(
#720000
0(
#730000
b110 G
b10 3
b10 H
b10 P
b11 4
b11 C
b11 O
11
b1001 J
b1001010 '
b1001010 -
b1001010 :
b1001010 &
b1001010 ,
b1001010 9
b100101 *
b100101 /
b100101 <
b100101 )
b100101 .
b100101 ;
1(
#740000
0(
#750000
b1001100 '
b1001100 -
b1001100 :
b1001100 &
b1001100 ,
b1001100 9
b100110 *
b100110 /
b100110 <
b100110 )
b100110 .
b100110 ;
b11 Q
b10 R
18
1T
01
1(
#760000
0(
#770000
b1 R
b11 !
b11 2
b11 S
0"
b1001110 '
b1001110 -
b1001110 :
b1001110 &
b1001110 ,
b1001110 9
b100111 *
b100111 /
b100111 <
b100111 )
b100111 .
b100111 ;
1(
#780000
b0 Q
1"
0(
#790000
b0 R
b0 !
b0 2
b0 S
b1010000 '
b1010000 -
b1010000 :
b1010000 &
b1010000 ,
b1010000 9
b101000 *
b101000 /
b101000 <
b101000 )
b101000 .
b101000 ;
0"
1(
#800000
0T
1"
0(
#810000
08
b1010010 '
b1010010 -
b1010010 :
b1010010 &
b1010010 ,
b1010010 9
b101001 *
b101001 /
b101001 <
b101001 )
b101001 .
b101001 ;
1(
#820000
0(
#830000
b1010100 '
b1010100 -
b1010100 :
b1010100 &
b1010100 ,
b1010100 9
b101010 *
b101010 /
b101010 <
b101010 )
b101010 .
b101010 ;
b110 J
1(
#840000
0(
#850000
b0 I
b100000000 4
b100000000 C
b100000000 O
b110 3
b110 H
b110 P
11
1F
b1 G
b1001 J
b1010110 '
b1010110 -
b1010110 :
b1010110 &
b1010110 ,
b1010110 9
b101011 *
b101011 /
b101011 <
b101011 )
b101011 .
b101011 ;
1(
#860000
0(
#870000
b1011000 '
b1011000 -
b1011000 :
b1011000 &
b1011000 ,
b1011000 9
b101100 *
b101100 /
b101100 <
b101100 )
b101100 .
b101100 ;
b100000000 Q
b110 R
18
1T
01
1(
#880000
0(
