four_bit_spi.v
`timescale 1ns / 1ps
module four_bit_spi(
					 input 			  clock,
					 input 			  reset_n,
					 input 			  trigger,
					 input 			  four_bit,
					 output reg 	  busy,
					 input [5:0] 	  bits_to_send,
					 // 
					 input [63:0] 	  data_input,
					 // SPI interface
					 output reg 	  cs,
					 output 		  sclk,
					 output reg [3:0] sdio
);

   // where to put initiation of send
   parameter
	 STATE_IDLE = 0,
	 STATE_SEND = 1;

   reg [1:0] 						  state;
   reg [5:0] 						  bits_cntr;
   reg [63:0] 						  data_send;

   reg 								  triggered;

   initial begin
	  cs = 0;
   end

   reg pos;
   reg neg;

   assign sclk = !(neg^pos);
   // Phase of sclk is constant because reset_n is evaluated at the edge of clock.
   always @(posedge clock)begin
	  if(~reset_n) pos <= 0;
	  else begin
		 if(state == STATE_SEND) pos <= ~pos;

	  end
   end

   always @(negedge clock)begin
	  if(~reset_n) begin
		 neg <= 0;
	  end
	  else begin
		 if(state == STATE_SEND) neg <= ~neg;
	  end
   end

   // handle statemachine transition
   always @(posedge clock) begin
	  if(~reset_n) begin
		 state <= STATE_IDLE;
		 triggered <= 0;
		 busy <= 0;
	  end
	  case(state)
		STATE_IDLE : begin
		   if(trigger & ~busy) begin
			  busy <=1 ;
			  triggered <= 1;
			  state <= STATE_SEND;
		   end else begin
			  busy <= 0;
			  triggered <= 0;
		   end
		end
		STATE_SEND : begin
		   busy <= 1;
		   triggered <= 0;
		   if(bits_cntr == 0) begin
			  state <= STATE_IDLE;
		   end
		end
	  endcase // case (state)
   end // always @ (posedge clock)

   always @(negedge sclk) begin
	  if(~reset_n) begin
		 sdio <= 4'b0;
	  end else begin
		 case(state)
		   STATE_IDLE : begin
			  sdio <= 4'b0;
		   end

		   STATE_SEND : begin
			  if(four_bit) begin
				 if(triggered) begin
					/*sdio[0] <= data_input[0];
					 sdio[1] <= data_input[1];
					 sdio[2] <= data_input[2];
					 sdio[3] <= data_input[3];
					 */
					sdio[0] <= data_input[bits_to_send-4];
					sdio[1] <= data_input[bits_to_send-3];
					sdio[2] <= data_input[bits_to_send-2];
					sdio[3] <= data_input[bits_to_send-1];
					bits_cntr <= bits_to_send - 4;
					data_send <= (data_input >> 4);
				 end else begin // if (triggered)
					/*
					 sdio[0] <= data_send[0];
					 sdio[1] <= data_send[1];
					 sdio[2] <= data_send[2];
					 sdio[3] <= data_send[3];
					 */
					sdio[0] <= data_input[bits_cntr-4];
					sdio[1] <= data_input[bits_cntr-3];
					sdio[2] <= data_input[bits_cntr-2];
					sdio[3] <= data_input[bits_cntr-1];
					bits_cntr <= bits_cntr - 4;
					data_send <= (data_send >> 4);
				 end // else: !if(triggered)
			  end else begin // if (four_bit)
				 if(triggered) begin
					sdio[0] <= data_input[bits_to_send -1];
					sdio[1] <= 0;
					sdio[2] <= 0;
					sdio[3] <= 0;
				   
					bits_cntr <= bits_to_send - 1;
					data_send <= (data_input >> 1);
				 end else begin
					sdio[0] <= data_input[bits_cntr -1];
					sdio[1] <= 0;
					sdio[2] <= 0;
					sdio[3] <= 0;
					
					bits_cntr <= bits_cntr - 1;
					data_send <= (data_send >> 1);
				 end
			  end // else: !if(four_bit)
		   end // case: STATE_SEND
		 endcase // case (state)
	  end // else: !if(~reset_n)
	  
   end // always @ (negedge sclk)
endmodule // four_bit_spi

four_bit_spi_tb.v
`timescale 1ns / 1ps

module four_bit_spi_tb;
   wire busy;
   wire cs;
   wire sclk;
   wire [3:0] sdio;

   reg 		 clock;
   reg 		 reset_n;
   reg 		 trigger;
   reg [5:0] bits_to_send;
   reg [63:0] data_input;

   reg 		  four_bit;
   
   
   four_bit_spi dut(/*AUTOINST*/
					// Outputs
					.busy				(busy),
					.cs					(cs),
					.sclk				(sclk),
					.sdio				(sdio[3:0]),
					// Inputs
					.clock				(clock),
					.reset_n			(reset_n),
					.trigger			(trigger),
					.four_bit			(four_bit),
					.bits_to_send		(bits_to_send[5:0]),
					.data_input			(data_input[63:0]));
   // clock generation   
   always begin
	  #10 	 clock = ~clock;
   end
   integer 	   i;


   initial begin
	  $dumpfile("four_bit_spi_tb.vcd");
	  $dumpvars(0, four_bit_spi_tb);
	  data_input = 0;
	  for(i = 0;i < 10; i = i+1)begin
	//	 data_input[i*4+3:i*4] <= i;
		 data_input = data_input | (i & 4'hF) << (i << 2);
	  end


	  
	  $display("START");
	  clock <= 0;
	  reset_n <= 0;
	  four_bit <= 0;
	  #100 reset_n <= 1;

	  #10 bits_to_send <= 40;

	  #10 trigger <= 1;

	  #20 trigger <= 0;

	  # 1000 trigger <= 1;
	  bits_to_send <= 40;
	  four_bit <= 1;
	  # 20 trigger <= 0;
	  
	  #10000
		$display("END");
	  $finish;
	  
   end // initial begin
   
   
endmodule // testbench

four_bit_spi_tb.vcd
$date
	Sat Jan 26 19:07:17 2019
$end
$version
	Icarus Verilog
$end
$timescale
	1ps
$end
$scope module four_bit_spi_tb $end
$var wire 4 ! sdio [3:0] $end
$var wire 1 " sclk $end
$var wire 1 # cs $end
$var wire 1 $ busy $end
$var reg 6 % bits_to_send [5:0] $end
$var reg 1 & clock $end
$var reg 64 ' data_input [63:0] $end
$var reg 1 ( four_bit $end
$var reg 1 ) reset_n $end
$var reg 1 * trigger $end
$var integer 32 + i [31:0] $end
$scope module dut $end
$var wire 6 , bits_to_send [5:0] $end
$var wire 1 & clock $end
$var wire 64 - data_input [63:0] $end
$var wire 1 ( four_bit $end
$var wire 1 ) reset_n $end
$var wire 1 * trigger $end
$var wire 1 " sclk $end
$var reg 6 . bits_cntr [5:0] $end
$var reg 1 $ busy $end
$var reg 1 # cs $end
$var reg 64 / data_send [63:0] $end
$var reg 1 0 neg $end
$var reg 1 1 pos $end
$var reg 4 2 sdio [3:0] $end
$var reg 2 3 state [1:0] $end
$var reg 1 4 triggered $end
$upscope $end
$upscope $end
$enddefinitions $end
#0
$dumpvars
x4
bx 3
bx 2
x1
00
bx /
bx .
b1001100001110110010101000011001000010000 -
bx ,
b1010 +
x*
0)
0(
b1001100001110110010101000011001000010000 '
0&
bx %
x$
0#
x"
bx !
$end
#10000
1"
01
0$
04
b0 3
1&
#20000
0&
#30000
1&
#40000
0&
#50000
1&
#60000
0&
#70000
1&
#80000
0&
#90000
1&
#100000
1)
0&
#110000
b101000 %
b101000 ,
1&
#120000
1*
0&
#130000
b1 3
14
1$
1&
#140000
b100110000111011001010100001100100001000 /
b100111 .
b1 !
b1 2
0"
10
0*
0&
#150000
1"
04
11
1&
#160000
b10011000011101100101010000110010000100 /
b100110 .
b0 !
b0 2
0"
00
0&
#170000
1"
01
1&
#180000
b1001100001110110010101000011001000010 /
b100101 .
0"
10
0&
#190000
1"
11
1&
#200000
b100110000111011001010100001100100001 /
b100100 .
b1 !
b1 2
0"
00
0&
#210000
1"
01
1&
#220000
b10011000011101100101010000110010000 /
b100011 .
0"
10
0&
#230000
1"
11
1&
#240000
b1001100001110110010101000011001000 /
b100010 .
b0 !
b0 2
0"
00
0&
#250000
1"
01
1&
#260000
b100110000111011001010100001100100 /
b100001 .
0"
10
0&
#270000
1"
11
1&
#280000
b10011000011101100101010000110010 /
b100000 .
0"
00
0&
#290000
1"
01
1&
#300000
b1001100001110110010101000011001 /
b11111 .
0"
10
0&
#310000
1"
11
1&
#320000
b100110000111011001010100001100 /
b11110 .
b1 !
b1 2
0"
00
0&
#330000
1"
01
1&
#340000
b10011000011101100101010000110 /
b11101 .
0"
10
0&
#350000
1"
11
1&
#360000
b1001100001110110010101000011 /
b11100 .
0"
00
0&
#370000
1"
01
1&
#380000
b100110000111011001010100001 /
b11011 .
b0 !
b0 2
0"
10
0&
#390000
1"
11
1&
#400000
b10011000011101100101010000 /
b11010 .
b1 !
b1 2
0"
00
0&
#410000
1"
01
1&
#420000
b1001100001110110010101000 /
b11001 .
0"
10
0&
#430000
1"
11
1&
#440000
b100110000111011001010100 /
b11000 .
b0 !
b0 2
0"
00
0&
#450000
1"
01
1&
#460000
b10011000011101100101010 /
b10111 .
0"
10
0&
#470000
1"
11
1&
#480000
b1001100001110110010101 /
b10110 .
b1 !
b1 2
0"
00
0&
#490000
1"
01
1&
#500000
b100110000111011001010 /
b10101 .
b0 !
b0 2
0"
10
0&
#510000
1"
11
1&
#520000
b10011000011101100101 /
b10100 .
b1 !
b1 2
0"
00
0&
#530000
1"
01
1&
#540000
b1001100001110110010 /
b10011 .
b0 !
b0 2
0"
10
0&
#550000
1"
11
1&
#560000
b100110000111011001 /
b10010 .
b1 !
b1 2
0"
00
0&
#570000
1"
01
1&
#580000
b10011000011101100 /
b10001 .
b0 !
b0 2
0"
10
0&
#590000
1"
11
1&
#600000
b1001100001110110 /
b10000 .
0"
00
0&
#610000
1"
01
1&
#620000
b100110000111011 /
b1111 .
0"
10
0&
#630000
1"
11
1&
#640000
b10011000011101 /
b1110 .
0"
00
0&
#650000
1"
01
1&
#660000
b1001100001110 /
b1101 .
b1 !
b1 2
0"
10
0&
#670000
1"
11
1&
#680000
b100110000111 /
b1100 .
0"
00
0&
#690000
1"
01
1&
#700000
b10011000011 /
b1011 .
b0 !
b0 2
0"
10
0&
#710000
1"
11
1&
#720000
b1001100001 /
b1010 .
0"
00
0&
#730000
1"
01
1&
#740000
b100110000 /
b1001 .
b1 !
b1 2
0"
10
0&
#750000
1"
11
1&
#760000
b10011000 /
b1000 .
b0 !
b0 2
0"
00
0&
#770000
1"
01
1&
#780000
b1001100 /
b111 .
0"
10
0&
#790000
1"
11
1&
#800000
b100110 /
b110 .
0"
00
0&
#810000
1"
01
1&
#820000
b10011 /
b101 .
0"
10
0&
#830000
1"
11
1&
#840000
b1001 /
b100 .
b1 !
b1 2
0"
00
0&
#850000
1"
01
1&
#860000
b100 /
b11 .
b0 !
b0 2
0"
10
0&
#870000
1"
11
1&
#880000
b10 /
b10 .
0"
00
0&
#890000
1"
01
1&
#900000
b1 /
b1 .
0"
10
0&
#910000
1"
11
1&
#920000
b0 /
b0 .
0"
00
0&
#930000
1"
01
b0 3
1&
#940000
0&
#950000
0$
1&
#960000
0&
#970000
1&
#980000
0&
#990000
1&
#1000000
0&
#1010000
1&
#1020000
0&
#1030000
1&
#1040000
0&
#1050000
1&
#1060000
0&
#1070000
1&
#1080000
0&
#1090000
1&
#1100000
0&
#1110000
1&
#1120000
0&
#1130000
1&
#1140000
1(
1*
0&
#1150000
b1 3
14
1$
1&
#1160000
b100110000111011001010100001100100001 /
b100100 .
b1001 !
b1001 2
0"
10
0*
0&
#1170000
1"
11
04
1&
#1180000
b10011000011101100101010000110010 /
b100000 .
b1000 !
b1000 2
0"
00
0&
#1190000
1"
01
1&
#1200000
b1001100001110110010101000011 /
b11100 .
b111 !
b111 2
0"
10
0&
#1210000
1"
11
1&
#1220000
b100110000111011001010100 /
b11000 .
b110 !
b110 2
0"
00
0&
#1230000
1"
01
1&
#1240000
b10011000011101100101 /
b10100 .
b101 !
b101 2
0"
10
0&
#1250000
1"
11
1&
#1260000
b1001100001110110 /
b10000 .
b100 !
b100 2
0"
00
0&
#1270000
1"
01
1&
#1280000
b100110000111 /
b1100 .
b11 !
b11 2
0"
10
0&
#1290000
1"
11
1&
#1300000
b10011000 /
b1000 .
b10 !
b10 2
0"
00
0&
#1310000
1"
01
1&
#1320000
b1001 /
b100 .
b1 !
b1 2
0"
10
0&
#1330000
1"
11
1&
#1340000
b0 /
b0 .
b0 !
b0 2
0"
00
0&
#1350000
1"
b0 3
01
1&
#1360000
0&
#1370000
0$
1&
