four_bit_spi.v
`timescale 1ns / 1ps
module four_bit_spi(
					 input 			  clock,
					 input 			  reset_n,
					 input 			  trigger,
					 output reg 	  busy,
					 input [4:0] 	  packs_to_send,
					 // 
					 input [63:0] 	  data_input,
					 // SPI interface
					 output reg 	  cs,
					 output reg 	  sclk,
					 output reg [3:0] sdio
);

   // where to put initiation of send
   parameter
	 STATE_IDLE = 0,
	 STATE_SEND = 1;

   reg [1:0] 						  state;
   reg [4:0] 						  packs_cntr;
   reg [63:0] 						  data_send;

   reg 								  triggered;

   initial begin
	  cs = 0;
   end

   always @(posedge clock or negedge clock) begin
	  if(~reset_n) begin
		 sclk <= 1'b1;
	  end else begin
		 case(state)
		   STATE_IDLE : begin
			  sclk <= 1'b1; //clock stall high
			  busy <= 0;
		   end
		   STATE_SEND : begin
			  sclk <= ~sclk;
			  busy <= 1;
		   end
		 endcase // case (state)
	  end
   end // always @ (posedge clock or negedge clock)

   // handle statemachine transition
   always @(posedge clock) begin
	  if(~reset_n) begin
		 state <= STATE_IDLE;
		 triggered <= 0;
	  end
	  case(state)
		STATE_IDLE : begin
		   if(trigger & ~busy) begin
			  triggered <= 1;
			  state <= STATE_SEND;
		   end else begin
			  triggered <= 0;
		   end
		end
		STATE_SEND : begin
		   triggered <= 0;
		   if(packs_cntr == 0) begin
			  state <= STATE_IDLE;
		   end
		end
	  endcase
   end


   always @(negedge sclk) begin
	  if(~reset_n) begin
		 sdio <= 4'b0;
	  end else begin
		 case(state)
		   STATE_IDLE : begin
			  sdio <= 4'b0;
		   end

		   STATE_SEND : begin
			  if(triggered) begin
				 sdio[0] <= data_input[0];
				 sdio[1] <= data_input[1];
				 sdio[2] <= data_input[2];
				 sdio[3] <= data_input[3];
				 packs_cntr <= packs_to_send - 1;
				 data_send <= (data_input >> 4);
			  end else begin
				 sdio[0] <= data_send[0];
				 sdio[1] <= data_send[1];
				 sdio[2] <= data_send[2];
				 sdio[3] <= data_send[3];
				 packs_cntr <= packs_cntr - 1;
				 data_send <= (data_send >> 4);
			  end // else: !if(triggered)
		   end
		 endcase // case (state)
	  end
	  
   end // always @ (negedge sclk)

   always @(posedge sclk) begin
	  
   end
endmodule

four_bit_spi_tb.v
`timescale 1ns / 1ps

module four_bit_spi_tb;
   wire busy;
   wire cs;
   wire sclk;
   wire [3:0] sdio;

   reg 		 clock;
   reg 		 reset_n;
   reg 		 trigger;
   reg [4:0] packs_to_send;
   reg [63:0] data_input;
   
   four_bit_spi dut(/*AUTOINST*/
					 // Outputs
					 .busy				(busy),
					 .cs				(cs),
					 .sclk				(sclk),
					 .sdio				(sdio[3:0]),
					 // Inputs
					 .clock				(clock),
					 .reset_n			(reset_n),
					 .trigger			(trigger),
					 .packs_to_send		(packs_to_send[4:0]),
					 .data_input		(data_input[63:0]));
   // clock generation   
   always begin
	  #10 	 clock = ~clock;
   end
   integer 	   i;


   initial begin
	  $dumpfile("four_bit_spi_tb.vcd");
	  $dumpvars(0, four_bit_spi_tb);
	  data_input = 0;
	  for(i = 0;i < 10; i = i+1)begin
	//	 data_input[i*4+3:i*4] <= i;
		 data_input = data_input | (i & 4'hF) << (i << 2);
	  end


	  
	  $display("START");
	  clock <= 0;
	  reset_n <= 0;
	  #100 reset_n <= 1;
	  #10 packs_to_send <= 10;

	  #10 trigger <= 1;

	  #20 trigger <= 0;

	  # 1000 trigger <= 1;
	  packs_to_send <= 10;
	  # 20 trigger <= 0;
	  
	  #10000
		$display("END");
	  $finish;
	  
   end // initial begin
   
   
endmodule // testbench

four_bit_spi_tb.vcd
$date
	Thu Jan 24 19:45:00 2019
$end
$version
	Icarus Verilog
$end
$timescale
	1ps
$end
$scope module four_bit_spi_tb $end
$var wire 4 ! sdio [3:0] $end
$var wire 1 " sclk $end
$var wire 1 # cs $end
$var wire 1 $ busy $end
$var reg 1 % clock $end
$var reg 64 & data_input [63:0] $end
$var reg 5 ' packs_to_send [4:0] $end
$var reg 1 ( reset_n $end
$var reg 1 ) trigger $end
$var integer 32 * i [31:0] $end
$scope module dut $end
$var wire 1 % clock $end
$var wire 64 + data_input [63:0] $end
$var wire 5 , packs_to_send [4:0] $end
$var wire 1 ( reset_n $end
$var wire 1 ) trigger $end
$var reg 1 $ busy $end
$var reg 1 # cs $end
$var reg 64 - data_send [63:0] $end
$var reg 5 . packs_cntr [4:0] $end
$var reg 1 " sclk $end
$var reg 4 / sdio [3:0] $end
$var reg 2 0 state [1:0] $end
$var reg 1 1 triggered $end
$upscope $end
$upscope $end
$enddefinitions $end
#0
$dumpvars
x1
bx 0
bx /
bx .
bx -
bx ,
b1001100001110110010101000011001000010000 +
b1010 *
x)
0(
bx '
b1001100001110110010101000011001000010000 &
0%
x$
0#
1"
bx !
$end
#10000
01
b0 0
1%
#20000
0%
#30000
1%
#40000
0%
#50000
1%
#60000
0%
#70000
1%
#80000
0%
#90000
1%
#100000
1(
0%
#110000
0$
b1010 '
b1010 ,
1%
#120000
1)
0%
#130000
b1 0
11
1%
#140000
b100110000111011001010100001100100001 -
b1001 .
b0 !
b0 /
1$
0"
0)
0%
#150000
01
1"
1%
#160000
b10011000011101100101010000110010 -
b1000 .
b1 !
b1 /
0"
0%
#170000
1"
1%
#180000
b1001100001110110010101000011 -
b111 .
b10 !
b10 /
0"
0%
#190000
1"
1%
#200000
b100110000111011001010100 -
b110 .
b11 !
b11 /
0"
0%
#210000
1"
1%
#220000
b10011000011101100101 -
b101 .
b100 !
b100 /
0"
0%
#230000
1"
1%
#240000
b1001100001110110 -
b100 .
b101 !
b101 /
0"
0%
#250000
1"
1%
#260000
b100110000111 -
b11 .
b110 !
b110 /
0"
0%
#270000
1"
1%
#280000
b10011000 -
b10 .
b111 !
b111 /
0"
0%
#290000
1"
1%
#300000
b1001 -
b1 .
b1000 !
b1000 /
0"
0%
#310000
1"
1%
#320000
b0 -
b0 .
b1001 !
b1001 /
0"
0%
#330000
b0 0
1"
1%
#340000
0$
0%
