spi_send_only.v
`timescale 1ns / 1ps
/* PASSED TEST */

/*
 * Send-only-spi module
 * 1 pack (= 4 bit) of data are read every posedge of sclk.
 * Send only, Clock stall high, update sdio on negedge of sclk.
 * Data is sent in LSB first
 * packs[0] -> sdio[0]
 * packs[1] -> sdio[1]
 * ..
 * 
 * Usage of this module
 * 1. Set data to send on data_input and packs_to_send. see manual for AD9958.
 * 2. set trigger high when busy is low.
 * 3. wait for busy turn to low before sending next data.
 */
module spi_send_only(
					 input 			  clock,
					 input 			  reset_n,
					 input 			  trigger,
					 output reg 	  busy,
					 input [4:0] 	  packs_to_send,
					 // 
					 input [63:0] 	  data_input,
					 // SPI interface
					 output reg 	  cs,
					 output reg 	  sclk,
					 output reg [3:0] sdio
);
   /* STATEMACHINE DEFINITION */
   parameter
	 STATE_IDLE = 0,
	 STATE_SEND = 1;

   reg 								  state;
   reg [4:0] 						  packs_cntr;

   // Send buffer
   reg [63:0] 						  data_send;
   
   
   // set to low by default
   //assign sdio = 4'b0;
   // clock stall high
   //assign sclk = 1'b1;
   
   always @(posedge clock) begin
	  if(~reset_n) begin
		 cs <= 0; // assuming single device is connected.		 
		 state <= STATE_IDLE;
		 busy <= 1;
		 sclk <= 1'b1;
		 sdio <= 4'b0;
		 packs_cntr <= 5'b0;
	  end else begin
		 case(state)
		   STATE_IDLE : begin
			  if(trigger & ~busy) begin
				 state <= STATE_SEND;
				 busy <= 1;
				 packs_cntr <= packs_to_send;
				 data_send <= data_input;				 
			  end else begin
				 busy <= 0;
				 sclk <= 1'b1;
				 sdio <= 4'b0;
				 packs_cntr <= 5'b0;
			  end // else: !if(trigger & ~busy)
		   end // case: STATE_IDLE
		   
		   STATE_SEND : begin
			  sclk <= 1'b0;
		   end
		   
		   default : begin
		   end
		 endcase // case (state)
	  end // else: !if(~reset_n)
   end // always @ (posedge clock)

   always @(negedge clock)begin
	  if(~reset_n) begin
	  end else begin
		 case(state)
		   STATE_IDLE : begin
		   end

		   STATE_SEND : begin
			  sclk <= 1'b1;
		   end

		   default :begin
		   end

		 endcase // case (state)
	  end // else: !if(~reset_n)
   end // always @ (negedge clock)

   /*
	* Update sdio registers.
	*/
   always @(negedge sclk) begin
	  if(~reset_n) begin
		 sdio <= 4'b0;
	  end else begin
		 case (state)
		   STATE_IDLE : begin
		   end

		   STATE_SEND : begin
			  // once sdio is updated, shift data_send @ posedge of sclk
			  sdio[0] <= data_send[0];
			  sdio[1] <= data_send[1];
			  sdio[2] <= data_send[2];
			  sdio[3] <= data_send[3];

			  packs_cntr <= packs_cntr - 1;
		   end

		   default : begin
		   end
		 endcase // case (state)
	  end // else: !if(~reset_n)
   end // always @ (negedge sclk)

   always @(posedge sclk) begin
	  case (state)
		STATE_IDLE :begin
		end

		STATE_SEND : begin
		   if(packs_cntr == 0) begin
			  data_send <= 64'h0;
			  state <= STATE_IDLE;
		   end else begin
			  // shift data for next pack
			  //data_send <= {4'b0, data_send[32:4]};
			  data_send <= (data_send >> 4);
		   end
		end
	  endcase // case (state)
   end // always @ (posedge sclk)
endmodule // spi_send_only

spi_send_only_tb.v
`timescale 1ns / 1ps

module spi_send_only_tb;
   wire busy;
   wire cs;
   wire sclk;
   wire [3:0] sdio;

   reg 		 clock;
   reg 		 reset_n;
   reg 		 trigger;
   reg [4:0] packs_to_send;
   reg [63:0] data_input;
   
   spi_send_only dut(/*AUTOINST*/
					 // Outputs
					 .busy				(busy),
					 .cs				(cs),
					 .sclk				(sclk),
					 .sdio				(sdio[3:0]),
					 // Inputs
					 .clock				(clock),
					 .reset_n			(reset_n),
					 .trigger			(trigger),
					 .packs_to_send		(packs_to_send[4:0]),
					 .data_input		(data_input[63:0]));
   // clock generation   
   always begin
	  #10 	 clock = ~clock;
   end
   integer 	   i;


   initial begin
	  $dumpfile("spi_send_only_tb.vcd");
	  $dumpvars(0, spi_send_only_tb);
	  data_input = 0;
	  for(i = 0;i < 10; i = i+1)begin
	//	 data_input[i*4+3:i*4] <= i;
		 data_input = data_input | (i & 4'hF) << (i << 2);
	  end


	  
	  $display("START");
	  clock <= 0;
	  reset_n <= 0;
	  #100 reset_n <= 1;
	  #10 packs_to_send <= 10;

	  #10 trigger <= 1;

	  #10 trigger <= 0;
	  
	  #10000
		$display("END");
	  $finish;
	  
   end // initial begin
   
   
endmodule // testbench

spi_send_only_tb.vcd
$date
	Wed Jan 23 14:49:57 2019
$end
$version
	Icarus Verilog
$end
$timescale
	1ps
$end
$scope module spi_send_only_tb $end
$var wire 4 ! sdio [3:0] $end
$var wire 1 " sclk $end
$var wire 1 # cs $end
$var wire 1 $ busy $end
$var reg 1 % clock $end
$var reg 64 & data_input [63:0] $end
$var reg 5 ' packs_to_send [4:0] $end
$var reg 1 ( reset_n $end
$var reg 1 ) trigger $end
$var integer 32 * i [31:0] $end
$scope module dut $end
$var wire 1 % clock $end
$var wire 64 + data_input [63:0] $end
$var wire 5 , packs_to_send [4:0] $end
$var wire 1 ( reset_n $end
$var wire 1 ) trigger $end
$var reg 1 $ busy $end
$var reg 1 # cs $end
$var reg 64 - data_send [63:0] $end
$var reg 5 . packs_cntr [4:0] $end
$var reg 1 " sclk $end
$var reg 4 / sdio [3:0] $end
$var reg 1 0 state $end
$upscope $end
$upscope $end
$enddefinitions $end
#0
$dumpvars
x0
bx /
bx .
bx -
bx ,
b1001100001110110010101000011001000010000 +
b1010 *
x)
0(
bx '
b1001100001110110010101000011001000010000 &
0%
x$
x#
x"
bx !
$end
#10000
b0 .
b0 !
b0 /
1"
1$
00
0#
1%
#20000
0%
#30000
1%
#40000
0%
#50000
1%
#60000
0%
#70000
1%
#80000
0%
#90000
1%
#100000
1(
0%
#110000
0$
b1010 '
b1010 ,
1%
#120000
1)
0%
#130000
b1001100001110110010101000011001000010000 -
b1010 .
1$
10
0)
1%
#140000
0%
#150000
b1001 .
0"
1%
#160000
b100110000111011001010100001100100001 -
1"
0%
#170000
b1000 .
b1 !
b1 /
0"
1%
#180000
b10011000011101100101010000110010 -
1"
0%
#190000
b111 .
b10 !
b10 /
0"
1%
#200000
b1001100001110110010101000011 -
1"
0%
#210000
b110 .
b11 !
b11 /
0"
1%
#220000
b100110000111011001010100 -
1"
0%
#230000
b101 .
b100 !
b100 /
0"
1%
#240000
b10011000011101100101 -
1"
0%
#250000
b100 .
b101 !
b101 /
0"
1%
#260000
b1001100001110110 -
1"
0%
#270000
b11 .
b110 !
b110 /
0"
1%
#280000
b100110000111 -
1"
0%
#290000
b10 .
b111 !
b111 /
0"
1%
#300000
b10011000 -
1"
0%
#310000
b1 .
b1000 !
b1000 /
0"
1%
#320000
b1001 -
1"
0%
#330000
b0 .
b1001 !
b1001 /
0"
1%
#340000
00
b0 -
1"
0%
#350000
b0 !
b0 /
0$
1%
